LICENSE.txt
README.md
rasa/__init__.py
rasa/__main__.py
rasa/api.py
rasa/cli/__init__.py
rasa/cli/arguments/__init__.py
rasa/cli/arguments/data.py
rasa/cli/arguments/default_arguments.py
rasa/cli/arguments/evaluate.py
rasa/cli/arguments/export.py
rasa/cli/arguments/interactive.py
rasa/cli/arguments/run.py
rasa/cli/arguments/shell.py
rasa/cli/arguments/test.py
rasa/cli/arguments/train.py
rasa/cli/arguments/visualize.py
rasa/cli/arguments/x.py
rasa/cli/data.py
rasa/cli/evaluate.py
rasa/cli/export.py
rasa/cli/initial_project/actions/__init__.py
rasa/cli/initial_project/actions/actions.py
rasa/cli/initial_project/config.yml
rasa/cli/initial_project/credentials.yml
rasa/cli/initial_project/data/nlu.yml
rasa/cli/initial_project/data/rules.yml
rasa/cli/initial_project/data/stories.yml
rasa/cli/initial_project/domain.yml
rasa/cli/initial_project/endpoints.yml
rasa/cli/initial_project/tests/test_stories.yml
rasa/cli/interactive.py
rasa/cli/run.py
rasa/cli/scaffold.py
rasa/cli/shell.py
rasa/cli/telemetry.py
rasa/cli/test.py
rasa/cli/train.py
rasa/cli/utils.py
rasa/cli/visualize.py
rasa/cli/x.py
rasa/constants.py
rasa/core/__init__.py
rasa/core/actions/__init__.py
rasa/core/actions/action.py
rasa/core/actions/constants.py
rasa/core/actions/forms.py
rasa/core/actions/loops.py
rasa/core/actions/two_stage_fallback.py
rasa/core/agent.py
rasa/core/brokers/__init__.py
rasa/core/brokers/broker.py
rasa/core/brokers/file.py
rasa/core/brokers/kafka.py
rasa/core/brokers/pika.py
rasa/core/brokers/sql.py
rasa/core/channels/__init__.py
rasa/core/channels/botframework.py
rasa/core/channels/callback.py
rasa/core/channels/channel.py
rasa/core/channels/console.py
rasa/core/channels/facebook.py
rasa/core/channels/hangouts.py
rasa/core/channels/mattermost.py
rasa/core/channels/rasa_chat.py
rasa/core/channels/rest.py
rasa/core/channels/rocketchat.py
rasa/core/channels/slack.py
rasa/core/channels/socketio.py
rasa/core/channels/telegram.py
rasa/core/channels/twilio.py
rasa-3.6.19.dist-info/LICENSE.txt
rasa-3.6.19.dist-info/METADATA
rasa-3.6.19.dist-info/WHEEL
rasa-3.6.19.dist-info/entry_points.txt
rasa-3.6.19.dist-info/RECORD
