Metadata-Version: 2.1
Name: rasa
Version: 3.6.19
Summary: Open source machine learning framework to automate text- and voice-based conversations: NLU, dialogue management, connect to Slack, Facebook, and more - Create chatbots and voice assistants
Home-page: https://rasa.com
License: Apache-2.0
Keywords: nlp,machine-learning,machine-learning-library,bot,bots,botkit,rasa conversational-agents,conversational-ai,chatbot,chatbot-framework,bot-framework
Author: Rasa Technologies GmbH
Author-email: hi@rasa.com
Maintainer: Tom Bocklisch
Maintainer-email: tom@rasa.com
Requires-Python: >=3.8,<3.11
Classifier: Development Status :: 5 - Production/Stable
Classifier: Intended Audience :: Developers
Classifier: License :: OSI Approved :: Apache Software License
Classifier: Programming Language :: Python :: 3
Classifier: Programming Language :: Python :: 3.8
Classifier: Programming Language :: Python :: 3.9
Classifier: Programming Language :: Python :: 3.10
Classifier: Topic :: Software Development :: Libraries
Provides-Extra: full
Provides-Extra: gh-release-notes
Provides-Extra: jieba
Provides-Extra: metal
Provides-Extra: spacy
Provides-Extra: transformers
Requires-Dist: CacheControl (>=0.12.9,<0.13.0)
Requires-Dist: PyJWT[crypto] (>=2.0.0,<3.0.0)
Requires-Dist: SQLAlchemy (>=1.4.0,<1.5.0)
Requires-Dist: absl-py (>=0.9,<1.5)
Requires-Dist: aio-pika (>=6.7.1,<8.2.4)
Requires-Dist: aiogram (<2.26)
Requires-Dist: aiohttp (>=3.9.0,<3.10)
Requires-Dist: apscheduler (>=3.6,<3.10)
Requires-Dist: attrs (>=19.3,<22.2)
Requires-Dist: boto3 (>=1.26.136,<2.0.0)
Requires-Dist: certifi (>=2023.7.22)
Requires-Dist: cloudpickle (>=1.2,<2.3)
Requires-Dist: colorama (>=0.4.4,<0.5.0) ; sys_platform == "win32"
Requires-Dist: colorclass (>=2.2,<2.3)
Requires-Dist: coloredlogs (>=10,<16)
Requires-Dist: colorhash (>=1.0.2,<1.3.0)
Requires-Dist: confluent-kafka (>=1.9.2,<3.0.0)
Requires-Dist: cryptography (>=41.0.7)
Requires-Dist: dask (==2022.10.2) ; python_version >= "3.8" and python_version < "3.11"
Requires-Dist: dask (==2022.2.0) ; python_full_version >= "3.7.0" and python_full_version < "3.8.0"
Requires-Dist: dnspython (==2.3.0)
Requires-Dist: fbmessenger (>=6.0.0,<6.1.0)
Requires-Dist: github3.py (>=3.2.0,<3.3.0) ; extra == "gh-release-notes"
Requires-Dist: google-auth (<3)
Requires-Dist: jieba (>=0.39,<0.43) ; extra == "jieba" or extra == "full"
Requires-Dist: joblib (>=0.15.1,<1.3.0)
Requires-Dist: jsonpickle (>=1.3,<3.1)
Requires-Dist: jsonschema (>=3.2,<4.18)
Requires-Dist: matplotlib (>=3.1,<3.6)
Requires-Dist: mattermostwrapper (>=2.2,<2.3)
Requires-Dist: networkx (>=2.4,<2.7)
Requires-Dist: numpy (==1.22.3) ; sys_platform == "Windows" and platform_python_implementation != "PyPy" and python_version == "3.10"
Requires-Dist: numpy (>=1.19.2,<1.22.0) ; python_full_version >= "3.7.0" and python_full_version < "3.8.0"
Requires-Dist: numpy (>=1.19.2,<1.25.0) ; python_version >= "3.8" and python_version < "3.11"
Requires-Dist: packaging (>=20.0,<21.0)
Requires-Dist: pluggy (>=1.0.0,<2.0.0)
Requires-Dist: portalocker (>=2.7.0,<3.0.0)
Requires-Dist: prompt-toolkit (>=3.0,<3.0.29)
Requires-Dist: protobuf (>=4.23.3,<4.23.4)
Requires-Dist: psycopg2-binary (>=2.8.2,<2.10.0)
Requires-Dist: pydantic (<1.10.10)
Requires-Dist: pydot (>=1.4,<1.5)
Requires-Dist: pykwalify (>=1.7,<1.9)
Requires-Dist: pymongo[srv,tls] (>=3.8,<4.4)
Requires-Dist: python-dateutil (>=2.8,<2.9)
Requires-Dist: python-engineio (>=4,<6,!=5.0.0)
Requires-Dist: python-socketio (>=4.4,<6)
Requires-Dist: pytz (>=2019.1,<2023.0)
Requires-Dist: pyyaml (>=6.0)
Requires-Dist: questionary (>=1.5.1,<1.11.0)
Requires-Dist: randomname (>=0.1.5,<0.2.0)
Requires-Dist: rasa-sdk (>=3.6.2,<3.7.0)
Requires-Dist: redis (>=4.5.3,<5.0)
Requires-Dist: regex (>=2020.6,<2022.11)
Requires-Dist: requests (>=2.23,<3.0)
Requires-Dist: rocketchat_API (>=0.6.31,<1.31.0)
Requires-Dist: ruamel.yaml (>=0.16.5,<0.17.22)
Requires-Dist: sanic (>=21.12,<21.13)
Requires-Dist: sanic-cors (>=2.0.0,<2.1.0)
Requires-Dist: sanic-jwt (>=1.6.0,<2.0.0)
Requires-Dist: sanic-routing (>=0.7.2,<0.8.0)
Requires-Dist: scikit-learn (>=0.22,<1.1) ; python_full_version >= "3.7.0" and python_full_version < "3.8.0"
Requires-Dist: scikit-learn (>=0.22,<1.2) ; python_version >= "3.8" and python_version < "3.11"
Requires-Dist: scipy (>=1.10.0) ; python_version >= "3.8" and python_version < "3.11"
Requires-Dist: scipy (>=1.4.1,<1.7.3) ; python_full_version >= "3.7.0" and python_full_version < "3.8.0"
Requires-Dist: sentencepiece[sentencepiece] (>=0.1.99,<0.2.0) ; extra == "transformers" or extra == "full"
Requires-Dist: sentry-sdk (>=0.17.0,<1.15.0)
Requires-Dist: setuptools (>=65.5.1)
Requires-Dist: sklearn-crfsuite (>=0.3,<0.4)
Requires-Dist: slack-sdk (>=3.19.2,<4.0.0)
Requires-Dist: spacy (>=3.1,<3.5) ; (sys_platform != "darwin" or platform_machine != "arm64") and (extra == "spacy" or extra == "full")
Requires-Dist: spacy (>=3.4,<4.0) ; (sys_platform == "darwin" and platform_machine == "arm64") and (extra == "spacy" or extra == "full")
Requires-Dist: structlog (>=23.1.0,<24.0.0)
Requires-Dist: structlog-sentry (>=2.0.2,<3.0.0)
Requires-Dist: tarsafe (>=0.0.3,<0.0.5)
Requires-Dist: tensorflow (==2.12.0) ; sys_platform != "darwin" or platform_machine != "arm64"
Requires-Dist: tensorflow-cpu-aws (==2.12.0) ; sys_platform == "linux" and platform_machine == "arm64" or sys_platform == "linux" and platform_machine == "aarch64"
Requires-Dist: tensorflow-intel (==2.12.0) ; sys_platform == "win32"
Requires-Dist: tensorflow-io-gcs-filesystem (==0.31) ; sys_platform == "win32"
Requires-Dist: tensorflow-io-gcs-filesystem (==0.32) ; sys_platform == "darwin" and platform_machine != "arm64"
Requires-Dist: tensorflow-io-gcs-filesystem (==0.32) ; sys_platform == "linux"
Requires-Dist: tensorflow-macos (==2.12.0) ; sys_platform == "darwin" and platform_machine == "arm64"
Requires-Dist: tensorflow-metal (==0.8.0) ; (sys_platform == "darwin" and platform_machine == "arm64") and (extra == "metal")
Requires-Dist: tensorflow-text (==2.12.0) ; sys_platform != "win32" and platform_machine != "arm64" and platform_machine != "aarch64"
Requires-Dist: tensorflow_hub (>=0.13.0,<0.14.0)
Requires-Dist: terminaltables (>=3.1.0,<3.2.0)
Requires-Dist: tqdm (>=4.31,<5.0)
Requires-Dist: transformers (>=4.13.0,<=4.26.0) ; extra == "transformers" or extra == "full"
Requires-Dist: twilio (>=6.26,<8.3)
Requires-Dist: typing-extensions (>=4.1.1,<5.0.0)
Requires-Dist: typing-utils (>=0.1.0,<0.2.0)
Requires-Dist: ujson (>=1.35,<6.0)
Requires-Dist: webexteamssdk (>=1.1.1,<1.7.0)
Requires-Dist: websockets (>=10.0,<11.0)
Requires-Dist: wheel (>=0.38.1)
Project-URL: Documentation, https://rasa.com/docs
Project-URL: Repository, https://github.com/rasahq/rasa
